chatbot_session_flow/__init__.py
chatbot_session_flow/admin.py
chatbot_session_flow/apps.py
chatbot_session_flow/context_processors.py
chatbot_session_flow/middleware.py
chatbot_session_flow/models.py
chatbot_session_flow/urls.py
chatbot_session_flow/views.py
chatbot_session_flow/migrations/__init__.py
chatbot_session_flow-0.1.13.dist-info/licenses/LICENSE
chatbot_session_flow-0.1.13.dist-info/METADATA
chatbot_session_flow-0.1.13.dist-info/WHEEL
chatbot_session_flow-0.1.13.dist-info/top_level.txt
chatbot_session_flow-0.1.13.dist-info/RECORD
