Metadata-Version: 2.4
Name: chatbot_session_flow
Version: 0.1.13
Summary: A django Whatsapp chatbot session manager
Home-page: https://github.com/DK-denno/whatsapp-chatbot.git
Author: Dennis Kamau
Author-email: kamadennis05@gmail.com
Classifier: Framework :: Django
Classifier: Programming Language :: Python :: 3
Classifier: License :: OSI Approved :: MIT License
Classifier: Operating System :: OS Independent
Requires-Python: >=3.10
License-File: LICENSE
Requires-Dist: Django>=4.1.2
Dynamic: author
Dynamic: author-email
Dynamic: classifier
Dynamic: description
Dynamic: description-content-type
Dynamic: home-page
Dynamic: license-file
Dynamic: requires-dist
Dynamic: requires-python
Dynamic: summary
